game_sir_fixer/__init__.py
game_sir_fixer/helpers.py
game_sir_fixer/main.py
game_sir_fixer-0.0.1.dist-info/METADATA
game_sir_fixer-0.0.1.dist-info/WHEEL
game_sir_fixer-0.0.1.dist-info/top_level.txt
game_sir_fixer-0.0.1.dist-info/RECORD
