Metadata-Version: 2.1
Name: game-sir-fixer
Version: 0.0.1
Summary: A hacky workaround for the Game Sir wireless controller to interface with Dolphin Emulator
Home-page: https://github.com/GrantGMiller/game_sir_fixer
Author: Grant miller
Author-email: grant@grant-miller.com
License: PSF
Project-URL: Source Code, https://github.com/GrantGMiller/game_sir_fixer
Keywords: grant miller game sir dolphin emulator
Platform: UNKNOWN
Requires-Dist: pygame
Requires-Dist: pyvjoy
